openquantum_sdk/__init__.py
openquantum_sdk/__main__.py
openquantum_sdk/auth.py
openquantum_sdk/clients.py
openquantum_sdk/enums.py
openquantum_sdk/models.py
openquantum_sdk/utils.py
openquantum_sdk/qiskit/__init__.py
openquantum_sdk-0.3.1.dist-info/METADATA
openquantum_sdk-0.3.1.dist-info/WHEEL
openquantum_sdk-0.3.1.dist-info/entry_points.txt
openquantum_sdk-0.3.1.dist-info/top_level.txt
openquantum_sdk-0.3.1.dist-info/RECORD
