Metadata-Version: 2.4
Name: openquantum-sdk
Version: 0.3.1
Summary: Python SDK for Open Quantum
Classifier: Programming Language :: Python :: 3
Classifier: License :: OSI Approved :: Apache Software License
Classifier: Operating System :: OS Independent
Requires-Python: >=3.8
Requires-Dist: requests>=2.25.0
